cc_toolkit/__init__.py
cc_toolkit/redis_utils.py
cc_toolkit/utils.py
cc_toolkit-0.2.1.dist-info/licenses/LICENSE
cc_toolkit-0.2.1.dist-info/METADATA
cc_toolkit-0.2.1.dist-info/WHEEL
cc_toolkit-0.2.1.dist-info/top_level.txt
cc_toolkit-0.2.1.dist-info/RECORD
