Metadata-Version: 2.4
Name: cc-toolkit
Version: 0.2.1
Summary: A Python toolkit for common tasks, including Redis operations
Author-email: cuibo <yzf@cuibo.com>
Project-URL: Homepage, https://github.com/yourusername/cc-toolkit
Project-URL: Bug Tracker, https://github.com/yourusername/cc-toolkit/issues
Classifier: Programming Language :: Python :: 3
Classifier: License :: OSI Approved :: MIT License
Classifier: Operating System :: OS Independent
Classifier: Topic :: Software Development :: Libraries :: Python Modules
Classifier: Topic :: Database
Requires-Python: >=3.7
License-File: LICENSE
Requires-Dist: redis>=4.0.0
Dynamic: license-file
